youtube_search/__init__.py
youtube_search-2.1.1.dist-info/LICENSE
youtube_search-2.1.1.dist-info/METADATA
youtube_search-2.1.1.dist-info/WHEEL
youtube_search-2.1.1.dist-info/top_level.txt
youtube_search-2.1.1.dist-info/RECORD
