Metadata-Version: 2.1
Name: youtube-search
Version: 2.1.1
Summary: Perform YouTube video searches without the API
Home-page: https://github.com/joetats/youtube_search
Author: Joe Tatusko
Author-email: tatuskojc@gmail.com
License: MIT
Classifier: License :: OSI Approved :: MIT License
Classifier: Programming Language :: Python :: 3
Classifier: Programming Language :: Python :: 3.7
Classifier: Programming Language :: Python :: 3.8
License-File: LICENSE
